votifier/__init__.py
votifier/votifier.py
votifier-0.0.1.dist-info/LICENSE
votifier-0.0.1.dist-info/METADATA
votifier-0.0.1.dist-info/WHEEL
votifier-0.0.1.dist-info/top_level.txt
votifier-0.0.1.dist-info/RECORD
