Metadata-Version: 2.1
Name: votifier
Version: 0.0.1
Summary: A Votifier v1 Client.
Author-email: Netherwhal <netherwhal@simplyvanilla.net>
Project-URL: Homepage, https://github.com/SimplyVanilla/votifier.py
Project-URL: Issues, https://github.com/SimplyVanilla/votifier.py/issues
Classifier: Programming Language :: Python :: 3
Classifier: License :: OSI Approved :: GNU General Public License v3 or later (GPLv3+)
Classifier: Operating System :: OS Independent
Requires-Python: >=3.8
License-File: LICENSE
Requires-Dist: rsa
